{
	"configurations" : 
	[
		{
			"directories" : 
			[
				{
					"build" : ".",
					"jsonFile" : "directory-.-Debug-d0094a50bb2071803777.json",
					"minimumCMakeVersion" : 
					{
						"string" : "3.24"
					},
					"projectIndex" : 0,
					"source" : ".",
					"targetIndexes" : 
					[
						0
					]
				}
			],
			"name" : "Debug",
			"projects" : 
			[
				{
					"directoryIndexes" : 
					[
						0
					],
					"name" : "ST7735s",
					"targetIndexes" : 
					[
						0
					]
				}
			],
			"targets" : 
			[
				{
					"directoryIndex" : 0,
					"id" : "ST7735s.elf::@6890427a1f51a3e7e1df",
					"jsonFile" : "target-ST7735s.elf-Debug-6d180096da992307a3f3.json",
					"name" : "ST7735s.elf",
					"projectIndex" : 0
				}
			]
		}
	],
	"kind" : "codemodel",
	"paths" : 
	{
		"build" : "C:/Users/symct/Desktop/program/ST7735s/cmake-build-debug",
		"source" : "C:/Users/symct/Desktop/program/ST7735s"
	},
	"version" : 
	{
		"major" : 2,
		"minor" : 4
	}
}
